import java.awt.event.ActionListener;

class MainFrame$6
  implements ActionListener
{
  MainFrame$6(MainFrame paramMainFrame) {}
  
  /* Error */
  public void actionPerformed(java.awt.event.ActionEvent arg0)
  {
    // Byte code:
    //   0: aload_0
    //   1: getfield 12	MainFrame$6:this$0	LMainFrame;
    //   4: invokestatic 23	MainFrame:access$1	(LMainFrame;)Ljavax/swing/JTextField;
    //   7: invokevirtual 29	javax/swing/JTextField:getText	()Ljava/lang/String;
    //   10: ldc 35
    //   12: invokevirtual 37	java/lang/String:equals	(Ljava/lang/Object;)Z
    //   15: ifeq +16 -> 31
    //   18: aload_0
    //   19: getfield 12	MainFrame$6:this$0	LMainFrame;
    //   22: invokestatic 43	MainFrame:access$2	(LMainFrame;)Ljavax/swing/JLabel;
    //   25: ldc 47
    //   27: invokevirtual 49	javax/swing/JLabel:setText	(Ljava/lang/String;)V
    //   30: return
    //   31: aload_0
    //   32: getfield 12	MainFrame$6:this$0	LMainFrame;
    //   35: invokestatic 55	MainFrame:access$8	(LMainFrame;)[B
    //   38: astore_2
    //   39: aload_2
    //   40: invokestatic 59	javax/xml/bind/DatatypeConverter:printBase64Binary	([B)Ljava/lang/String;
    //   43: ldc 65
    //   45: invokevirtual 67	java/lang/String:getBytes	(Ljava/lang/String;)[B
    //   48: astore_3
    //   49: ldc 35
    //   51: astore 4
    //   53: new 71	java/lang/StringBuilder
    //   56: dup
    //   57: aload_0
    //   58: getfield 12	MainFrame$6:this$0	LMainFrame;
    //   61: invokevirtual 73	MainFrame:generateRandomNumber	()I
    //   64: invokestatic 77	java/lang/Integer:toString	(I)Ljava/lang/String;
    //   67: invokestatic 83	java/lang/String:valueOf	(Ljava/lang/Object;)Ljava/lang/String;
    //   70: invokespecial 87	java/lang/StringBuilder:<init>	(Ljava/lang/String;)V
    //   73: ldc 89
    //   75: invokevirtual 91	java/lang/StringBuilder:append	(Ljava/lang/String;)Ljava/lang/StringBuilder;
    //   78: invokevirtual 95	java/lang/StringBuilder:toString	()Ljava/lang/String;
    //   81: astore 5
    //   83: aload_0
    //   84: getfield 12	MainFrame$6:this$0	LMainFrame;
    //   87: invokestatic 23	MainFrame:access$1	(LMainFrame;)Ljavax/swing/JTextField;
    //   90: invokevirtual 29	javax/swing/JTextField:getText	()Ljava/lang/String;
    //   93: astore 8
    //   95: aload_0
    //   96: getfield 12	MainFrame$6:this$0	LMainFrame;
    //   99: invokestatic 97	MainFrame:access$7	(LMainFrame;)Ljavax/swing/JCheckBox;
    //   102: invokevirtual 101	javax/swing/JCheckBox:isSelected	()Z
    //   105: ifeq +301 -> 406
    //   108: aload_0
    //   109: getfield 12	MainFrame$6:this$0	LMainFrame;
    //   112: invokestatic 107	MainFrame:access$6	(LMainFrame;)Ljavax/swing/JTextField;
    //   115: invokevirtual 29	javax/swing/JTextField:getText	()Ljava/lang/String;
    //   118: ldc 35
    //   120: invokevirtual 37	java/lang/String:equals	(Ljava/lang/Object;)Z
    //   123: ifeq +16 -> 139
    //   126: aload_0
    //   127: getfield 12	MainFrame$6:this$0	LMainFrame;
    //   130: invokestatic 43	MainFrame:access$2	(LMainFrame;)Ljavax/swing/JLabel;
    //   133: ldc 110
    //   135: invokevirtual 49	javax/swing/JLabel:setText	(Ljava/lang/String;)V
    //   138: return
    //   139: aload_0
    //   140: getfield 12	MainFrame$6:this$0	LMainFrame;
    //   143: invokestatic 107	MainFrame:access$6	(LMainFrame;)Ljavax/swing/JTextField;
    //   146: invokevirtual 29	javax/swing/JTextField:getText	()Ljava/lang/String;
    //   149: astore 9
    //   151: aconst_null
    //   152: astore 10
    //   154: ldc 35
    //   156: astore 11
    //   158: ldc 89
    //   160: astore 12
    //   162: new 112	java/io/BufferedReader
    //   165: dup
    //   166: new 114	java/io/FileReader
    //   169: dup
    //   170: aload 9
    //   172: invokespecial 116	java/io/FileReader:<init>	(Ljava/lang/String;)V
    //   175: invokespecial 117	java/io/BufferedReader:<init>	(Ljava/io/Reader;)V
    //   178: astore 10
    //   180: goto +64 -> 244
    //   183: aload 11
    //   185: aload 12
    //   187: invokevirtual 120	java/lang/String:split	(Ljava/lang/String;)[Ljava/lang/String;
    //   190: astore 13
    //   192: getstatic 124	java/lang/System:out	Ljava/io/PrintStream;
    //   195: aload 13
    //   197: invokestatic 130	java/util/Arrays:deepToString	([Ljava/lang/Object;)Ljava/lang/String;
    //   200: invokevirtual 136	java/io/PrintStream:println	(Ljava/lang/String;)V
    //   203: new 71	java/lang/StringBuilder
    //   206: dup
    //   207: aload 5
    //   209: invokestatic 83	java/lang/String:valueOf	(Ljava/lang/Object;)Ljava/lang/String;
    //   212: invokespecial 87	java/lang/StringBuilder:<init>	(Ljava/lang/String;)V
    //   215: aload 13
    //   217: iconst_1
    //   218: aaload
    //   219: invokevirtual 91	java/lang/StringBuilder:append	(Ljava/lang/String;)Ljava/lang/StringBuilder;
    //   222: ldc 89
    //   224: invokevirtual 91	java/lang/StringBuilder:append	(Ljava/lang/String;)Ljava/lang/StringBuilder;
    //   227: aload 13
    //   229: iconst_3
    //   230: aaload
    //   231: invokevirtual 91	java/lang/StringBuilder:append	(Ljava/lang/String;)Ljava/lang/StringBuilder;
    //   234: ldc 89
    //   236: invokevirtual 91	java/lang/StringBuilder:append	(Ljava/lang/String;)Ljava/lang/StringBuilder;
    //   239: invokevirtual 95	java/lang/StringBuilder:toString	()Ljava/lang/String;
    //   242: astore 5
    //   244: aload 10
    //   246: invokevirtual 141	java/io/BufferedReader:readLine	()Ljava/lang/String;
    //   249: dup
    //   250: astore 11
    //   252: ifnonnull -69 -> 183
    //   255: aload 4
    //   257: invokevirtual 144	java/lang/String:length	()I
    //   260: ifle +123 -> 383
    //   263: aload 4
    //   265: aload 4
    //   267: invokevirtual 144	java/lang/String:length	()I
    //   270: iconst_1
    //   271: isub
    //   272: invokevirtual 147	java/lang/String:charAt	(I)C
    //   275: bipush 44
    //   277: if_icmpne +106 -> 383
    //   280: aload 4
    //   282: iconst_0
    //   283: aload 4
    //   285: invokevirtual 144	java/lang/String:length	()I
    //   288: iconst_1
    //   289: isub
    //   290: invokevirtual 151	java/lang/String:substring	(II)Ljava/lang/String;
    //   293: astore 5
    //   295: goto +88 -> 383
    //   298: astore 13
    //   300: aload 13
    //   302: invokevirtual 155	java/io/FileNotFoundException:printStackTrace	()V
    //   305: aload 10
    //   307: ifnull +196 -> 503
    //   310: aload 10
    //   312: invokevirtual 160	java/io/BufferedReader:close	()V
    //   315: goto +188 -> 503
    //   318: astore 15
    //   320: aload 15
    //   322: invokevirtual 163	java/io/IOException:printStackTrace	()V
    //   325: goto +178 -> 503
    //   328: astore 13
    //   330: aload 13
    //   332: invokevirtual 163	java/io/IOException:printStackTrace	()V
    //   335: aload 10
    //   337: ifnull +166 -> 503
    //   340: aload 10
    //   342: invokevirtual 160	java/io/BufferedReader:close	()V
    //   345: goto +158 -> 503
    //   348: astore 15
    //   350: aload 15
    //   352: invokevirtual 163	java/io/IOException:printStackTrace	()V
    //   355: goto +148 -> 503
    //   358: astore 14
    //   360: aload 10
    //   362: ifnull +18 -> 380
    //   365: aload 10
    //   367: invokevirtual 160	java/io/BufferedReader:close	()V
    //   370: goto +10 -> 380
    //   373: astore 15
    //   375: aload 15
    //   377: invokevirtual 163	java/io/IOException:printStackTrace	()V
    //   380: aload 14
    //   382: athrow
    //   383: aload 10
    //   385: ifnull +118 -> 503
    //   388: aload 10
    //   390: invokevirtual 160	java/io/BufferedReader:close	()V
    //   393: goto +110 -> 503
    //   396: astore 15
    //   398: aload 15
    //   400: invokevirtual 163	java/io/IOException:printStackTrace	()V
    //   403: goto +100 -> 503
    //   406: aload_0
    //   407: getfield 12	MainFrame$6:this$0	LMainFrame;
    //   410: invokestatic 166	MainFrame:access$4	(LMainFrame;)Ljavax/swing/JTextField;
    //   413: invokevirtual 29	javax/swing/JTextField:getText	()Ljava/lang/String;
    //   416: ldc 35
    //   418: invokevirtual 37	java/lang/String:equals	(Ljava/lang/Object;)Z
    //   421: ifne +21 -> 442
    //   424: aload_0
    //   425: getfield 12	MainFrame$6:this$0	LMainFrame;
    //   428: invokestatic 169	MainFrame:access$3	(LMainFrame;)Ljavax/swing/JTextField;
    //   431: invokevirtual 29	javax/swing/JTextField:getText	()Ljava/lang/String;
    //   434: ldc 35
    //   436: invokevirtual 37	java/lang/String:equals	(Ljava/lang/Object;)Z
    //   439: ifeq +16 -> 455
    //   442: aload_0
    //   443: getfield 12	MainFrame$6:this$0	LMainFrame;
    //   446: invokestatic 43	MainFrame:access$2	(LMainFrame;)Ljavax/swing/JLabel;
    //   449: ldc -84
    //   451: invokevirtual 49	javax/swing/JLabel:setText	(Ljava/lang/String;)V
    //   454: return
    //   455: new 71	java/lang/StringBuilder
    //   458: dup
    //   459: aload 5
    //   461: invokestatic 83	java/lang/String:valueOf	(Ljava/lang/Object;)Ljava/lang/String;
    //   464: invokespecial 87	java/lang/StringBuilder:<init>	(Ljava/lang/String;)V
    //   467: aload_0
    //   468: getfield 12	MainFrame$6:this$0	LMainFrame;
    //   471: invokestatic 166	MainFrame:access$4	(LMainFrame;)Ljavax/swing/JTextField;
    //   474: invokevirtual 29	javax/swing/JTextField:getText	()Ljava/lang/String;
    //   477: invokevirtual 91	java/lang/StringBuilder:append	(Ljava/lang/String;)Ljava/lang/StringBuilder;
    //   480: ldc 89
    //   482: invokevirtual 91	java/lang/StringBuilder:append	(Ljava/lang/String;)Ljava/lang/StringBuilder;
    //   485: aload_0
    //   486: getfield 12	MainFrame$6:this$0	LMainFrame;
    //   489: invokestatic 169	MainFrame:access$3	(LMainFrame;)Ljavax/swing/JTextField;
    //   492: invokevirtual 29	javax/swing/JTextField:getText	()Ljava/lang/String;
    //   495: invokevirtual 91	java/lang/StringBuilder:append	(Ljava/lang/String;)Ljava/lang/StringBuilder;
    //   498: invokevirtual 95	java/lang/StringBuilder:toString	()Ljava/lang/String;
    //   501: astore 5
    //   503: new 71	java/lang/StringBuilder
    //   506: dup
    //   507: aload 5
    //   509: invokestatic 83	java/lang/String:valueOf	(Ljava/lang/Object;)Ljava/lang/String;
    //   512: invokespecial 87	java/lang/StringBuilder:<init>	(Ljava/lang/String;)V
    //   515: aload 8
    //   517: invokevirtual 91	java/lang/StringBuilder:append	(Ljava/lang/String;)Ljava/lang/StringBuilder;
    //   520: invokevirtual 95	java/lang/StringBuilder:toString	()Ljava/lang/String;
    //   523: ldc 65
    //   525: invokevirtual 67	java/lang/String:getBytes	(Ljava/lang/String;)[B
    //   528: astore 9
    //   530: new 71	java/lang/StringBuilder
    //   533: dup
    //   534: aload 5
    //   536: invokestatic 83	java/lang/String:valueOf	(Ljava/lang/Object;)Ljava/lang/String;
    //   539: invokespecial 87	java/lang/StringBuilder:<init>	(Ljava/lang/String;)V
    //   542: ldc -82
    //   544: invokevirtual 91	java/lang/StringBuilder:append	(Ljava/lang/String;)Ljava/lang/StringBuilder;
    //   547: new 38	java/lang/String
    //   550: dup
    //   551: aload 9
    //   553: invokestatic 176	MainFrame:getsha256	([B)[B
    //   556: invokestatic 59	javax/xml/bind/DatatypeConverter:printBase64Binary	([B)Ljava/lang/String;
    //   559: invokespecial 180	java/lang/String:<init>	(Ljava/lang/String;)V
    //   562: invokevirtual 91	java/lang/StringBuilder:append	(Ljava/lang/String;)Ljava/lang/StringBuilder;
    //   565: invokevirtual 95	java/lang/StringBuilder:toString	()Ljava/lang/String;
    //   568: astore 4
    //   570: aload_0
    //   571: getfield 12	MainFrame$6:this$0	LMainFrame;
    //   574: invokestatic 181	MainFrame:access$9	(LMainFrame;)Ljavax/swing/JTextPane;
    //   577: aload 4
    //   579: invokevirtual 185	javax/swing/JTextPane:setText	(Ljava/lang/String;)V
    //   582: getstatic 124	java/lang/System:out	Ljava/io/PrintStream;
    //   585: new 71	java/lang/StringBuilder
    //   588: dup
    //   589: ldc -68
    //   591: invokespecial 87	java/lang/StringBuilder:<init>	(Ljava/lang/String;)V
    //   594: aload 4
    //   596: invokevirtual 91	java/lang/StringBuilder:append	(Ljava/lang/String;)Ljava/lang/StringBuilder;
    //   599: invokevirtual 95	java/lang/StringBuilder:toString	()Ljava/lang/String;
    //   602: invokevirtual 136	java/io/PrintStream:println	(Ljava/lang/String;)V
    //   605: getstatic 124	java/lang/System:out	Ljava/io/PrintStream;
    //   608: new 71	java/lang/StringBuilder
    //   611: dup
    //   612: ldc -66
    //   614: invokespecial 87	java/lang/StringBuilder:<init>	(Ljava/lang/String;)V
    //   617: new 38	java/lang/String
    //   620: dup
    //   621: aload 8
    //   623: invokespecial 180	java/lang/String:<init>	(Ljava/lang/String;)V
    //   626: invokevirtual 91	java/lang/StringBuilder:append	(Ljava/lang/String;)Ljava/lang/StringBuilder;
    //   629: invokevirtual 95	java/lang/StringBuilder:toString	()Ljava/lang/String;
    //   632: invokevirtual 136	java/io/PrintStream:println	(Ljava/lang/String;)V
    //   635: getstatic 124	java/lang/System:out	Ljava/io/PrintStream;
    //   638: new 71	java/lang/StringBuilder
    //   641: dup
    //   642: ldc -64
    //   644: invokespecial 87	java/lang/StringBuilder:<init>	(Ljava/lang/String;)V
    //   647: new 38	java/lang/String
    //   650: dup
    //   651: aload 9
    //   653: invokespecial 194	java/lang/String:<init>	([B)V
    //   656: invokevirtual 91	java/lang/StringBuilder:append	(Ljava/lang/String;)Ljava/lang/StringBuilder;
    //   659: invokevirtual 95	java/lang/StringBuilder:toString	()Ljava/lang/String;
    //   662: invokevirtual 136	java/io/PrintStream:println	(Ljava/lang/String;)V
    //   665: goto +26 -> 691
    //   668: astore_2
    //   669: getstatic 124	java/lang/System:out	Ljava/io/PrintStream;
    //   672: aload_2
    //   673: invokevirtual 197	java/lang/Exception:getMessage	()Ljava/lang/String;
    //   676: invokevirtual 136	java/io/PrintStream:println	(Ljava/lang/String;)V
    //   679: aload_0
    //   680: getfield 12	MainFrame$6:this$0	LMainFrame;
    //   683: invokestatic 181	MainFrame:access$9	(LMainFrame;)Ljavax/swing/JTextPane;
    //   686: ldc -54
    //   688: invokevirtual 185	javax/swing/JTextPane:setText	(Ljava/lang/String;)V
    //   691: return
    // Line number table:
    //   Java source line #251	-> byte code offset #0
    //   Java source line #252	-> byte code offset #18
    //   Java source line #253	-> byte code offset #30
    //   Java source line #256	-> byte code offset #31
    //   Java source line #258	-> byte code offset #39
    //   Java source line #260	-> byte code offset #49
    //   Java source line #261	-> byte code offset #53
    //   Java source line #264	-> byte code offset #83
    //   Java source line #266	-> byte code offset #95
    //   Java source line #267	-> byte code offset #108
    //   Java source line #268	-> byte code offset #126
    //   Java source line #269	-> byte code offset #138
    //   Java source line #273	-> byte code offset #139
    //   Java source line #274	-> byte code offset #151
    //   Java source line #275	-> byte code offset #154
    //   Java source line #276	-> byte code offset #158
    //   Java source line #279	-> byte code offset #162
    //   Java source line #280	-> byte code offset #180
    //   Java source line #282	-> byte code offset #183
    //   Java source line #283	-> byte code offset #192
    //   Java source line #286	-> byte code offset #203
    //   Java source line #280	-> byte code offset #244
    //   Java source line #288	-> byte code offset #255
    //   Java source line #289	-> byte code offset #280
    //   Java source line #291	-> byte code offset #295
    //   Java source line #292	-> byte code offset #300
    //   Java source line #296	-> byte code offset #305
    //   Java source line #298	-> byte code offset #310
    //   Java source line #299	-> byte code offset #315
    //   Java source line #300	-> byte code offset #320
    //   Java source line #293	-> byte code offset #328
    //   Java source line #294	-> byte code offset #330
    //   Java source line #296	-> byte code offset #335
    //   Java source line #298	-> byte code offset #340
    //   Java source line #299	-> byte code offset #345
    //   Java source line #300	-> byte code offset #350
    //   Java source line #295	-> byte code offset #358
    //   Java source line #296	-> byte code offset #360
    //   Java source line #298	-> byte code offset #365
    //   Java source line #299	-> byte code offset #370
    //   Java source line #300	-> byte code offset #375
    //   Java source line #303	-> byte code offset #380
    //   Java source line #296	-> byte code offset #383
    //   Java source line #298	-> byte code offset #388
    //   Java source line #299	-> byte code offset #393
    //   Java source line #300	-> byte code offset #398
    //   Java source line #304	-> byte code offset #403
    //   Java source line #306	-> byte code offset #406
    //   Java source line #307	-> byte code offset #442
    //   Java source line #308	-> byte code offset #454
    //   Java source line #310	-> byte code offset #455
    //   Java source line #316	-> byte code offset #503
    //   Java source line #317	-> byte code offset #530
    //   Java source line #318	-> byte code offset #570
    //   Java source line #321	-> byte code offset #582
    //   Java source line #322	-> byte code offset #605
    //   Java source line #324	-> byte code offset #635
    //   Java source line #328	-> byte code offset #665
    //   Java source line #329	-> byte code offset #668
    //   Java source line #330	-> byte code offset #669
    //   Java source line #331	-> byte code offset #679
    //   Java source line #333	-> byte code offset #691
    // Local variable table:
    //   start	length	slot	name	signature
    //   0	692	0	this	6
    //   0	692	1	arg0	java.awt.event.ActionEvent
    //   38	2	2	salt	byte[]
    //   668	5	2	e	Exception
    //   48	2	3	base64salt	byte[]
    //   51	544	4	TAN	String
    //   81	454	5	tmp	String
    //   93	529	8	password	String
    //   149	22	9	csvFile	String
    //   528	124	9	sha	byte[]
    //   152	237	10	br	java.io.BufferedReader
    //   156	95	11	line	String
    //   160	26	12	cvsSplitBy	String
    //   190	38	13	transaction	String[]
    //   298	3	13	e	java.io.FileNotFoundException
    //   328	3	13	e	java.io.IOException
    //   358	23	14	localObject	Object
    //   318	3	15	e	java.io.IOException
    //   348	3	15	e	java.io.IOException
    //   373	3	15	e	java.io.IOException
    //   396	3	15	e	java.io.IOException
    // Exception table:
    //   from	to	target	type
    //   162	295	298	java/io/FileNotFoundException
    //   310	315	318	java/io/IOException
    //   162	295	328	java/io/IOException
    //   340	345	348	java/io/IOException
    //   162	305	358	finally
    //   328	335	358	finally
    //   365	370	373	java/io/IOException
    //   388	393	396	java/io/IOException
    //   31	138	668	java/lang/Exception
    //   139	454	668	java/lang/Exception
    //   455	665	668	java/lang/Exception
  }
}


/* Location:              /Users/stefankofler/Documents/phase4/SourceAndBinary-Team2-Phase3.zip/scs.jar!/MainFrame$6.class
 * Java compiler version: 7 (51.0)
 * JD-Core Version:       0.7.1
 */